target_s3/__init__.py
target_s3-0.1.0.dist-info/DESCRIPTION.rst
target_s3-0.1.0.dist-info/METADATA
target_s3-0.1.0.dist-info/RECORD
target_s3-0.1.0.dist-info/WHEEL
target_s3-0.1.0.dist-info/entry_points.txt
target_s3-0.1.0.dist-info/metadata.json
target_s3-0.1.0.dist-info/top_level.txt
