Metadata-Version: 2.0
Name: target-s3
Version: 0.1.0
Summary: Singer.io target for the S3
Home-page: https://singer.io
Author: scirner22
Author-email: UNKNOWN
License: UNKNOWN
Platform: UNKNOWN
Classifier: Programming Language :: Python :: 3 :: Only
Requires-Dist: boto3 (==1.5.26)
Requires-Dist: jsonschema (==2.6.0)
Requires-Dist: singer-python (==5.0.2)
